blockfrost/__init__.py
blockfrost/config.py
blockfrost/helpers.py
blockfrost/utils.py
blockfrost/api/__init__.py
blockfrost/api/health.py
blockfrost/api/metrics.py
blockfrost/api/nutlink.py
blockfrost/api/cardano/__init__.py
blockfrost/api/cardano/accounts.py
blockfrost/api/cardano/addresses.py
blockfrost/api/cardano/assets.py
blockfrost/api/cardano/blocks.py
blockfrost/api/cardano/epochs.py
blockfrost/api/cardano/ledger.py
blockfrost/api/cardano/metadata.py
blockfrost/api/cardano/network.py
blockfrost/api/cardano/pools.py
blockfrost/api/cardano/scripts.py
blockfrost/api/cardano/transactions.py
blockfrost/api/cardano/utils.py
blockfrost/ipfs/__init__.py
blockfrost/ipfs/add.py
blockfrost/ipfs/gateway.py
blockfrost/ipfs/pins.py
blockfrost_python-0.5.3.dist-info/LICENSE
blockfrost_python-0.5.3.dist-info/METADATA
blockfrost_python-0.5.3.dist-info/WHEEL
blockfrost_python-0.5.3.dist-info/top_level.txt
blockfrost_python-0.5.3.dist-info/RECORD
