Metadata-Version: 2.1
Name: blockfrost-python
Version: 0.5.3
Summary: The official Python SDK for Blockfrost API v0.1.37
Home-page: https://github.com/blockfrost/blockfrost-python
Author: blockfrost.io
Author-email: contact@blockfrost.io
License: Apache-2.0
Keywords: blockfrost blockchain cardano ipfs
Classifier: Development Status :: 4 - Beta
Classifier: Intended Audience :: Developers
Classifier: Topic :: Software Development :: Build Tools
Classifier: License :: OSI Approved :: Apache Software License
Classifier: Programming Language :: Python :: 3
Classifier: Programming Language :: Python :: 3.7
Classifier: Programming Language :: Python :: 3.8
Classifier: Programming Language :: Python :: 3.9
Classifier: Programming Language :: Python :: 3.10
Classifier: Programming Language :: Python :: 3 :: Only
Requires-Python: >=3.7, <4
License-File: LICENSE
